pyloops/__init__.py
pyloops/_generated/__init__.py
pyloops/_generated/api/__init__.py
pyloops/_generated/api/api_key/__init__.py
pyloops/_generated/api/api_key/get_api_key.py
pyloops/_generated/api/contact_properties/__init__.py
pyloops/_generated/api/contact_properties/get_contacts_properties.py
pyloops/_generated/api/contact_properties/post_contacts_properties.py
pyloops/_generated/api/contacts/__init__.py
pyloops/_generated/api/contacts/get_contacts_find.py
pyloops/_generated/api/contacts/post_contacts_create.py
pyloops/_generated/api/contacts/post_contacts_delete.py
pyloops/_generated/api/contacts/put_contacts_update.py
pyloops/_generated/api/dedicated_sending_i_ps/__init__.py
pyloops/_generated/api/dedicated_sending_i_ps/get_dedicated_sending_ips.py
pyloops/_generated/api/events/__init__.py
pyloops/_generated/api/events/post_events_send.py
pyloops/_generated/api/mailing_lists/__init__.py
pyloops/_generated/api/mailing_lists/get_lists.py
pyloops/_generated/api/transactional_emails/__init__.py
pyloops/_generated/api/transactional_emails/get_transactional.py
pyloops/_generated/api/transactional_emails/post_transactional.py
pyloops/_generated/client.py
pyloops/_generated/errors.py
pyloops/_generated/models/__init__.py
pyloops/_generated/models/contact.py
pyloops/_generated/models/contact_delete_request.py
pyloops/_generated/models/contact_delete_response.py
pyloops/_generated/models/contact_failure_response.py
pyloops/_generated/models/contact_mailing_lists.py
pyloops/_generated/models/contact_opt_in_status_type_1.py
pyloops/_generated/models/contact_opt_in_status_type_2_type_1.py
pyloops/_generated/models/contact_opt_in_status_type_3_type_1.py
pyloops/_generated/models/contact_property.py
pyloops/_generated/models/contact_property_create_request.py
pyloops/_generated/models/contact_property_failure_response.py
pyloops/_generated/models/contact_property_success_response.py
pyloops/_generated/models/contact_request.py
pyloops-1.7.0.dist-info/WHEEL
pyloops-1.7.0.dist-info/METADATA
pyloops-1.7.0.dist-info/RECORD
