Metadata-Version: 2.3
Name: pyloops
Version: 1.7.0
Summary: Unofficial Python SDK for Loops.so email platform
Keywords: loops,email,api,sdk,loops.so
Author: zegerius
Author-email: zegerius <aram@askaletta.com>
License: MIT
Classifier: Development Status :: 4 - Beta
Classifier: Intended Audience :: Developers
Classifier: License :: OSI Approved :: MIT License
Classifier: Programming Language :: Python :: 3
Classifier: Programming Language :: Python :: 3.12
Classifier: Programming Language :: Python :: 3.13
Classifier: Programming Language :: Python :: 3.14
Requires-Dist: httpx>=0.23.0,<0.29.0
Requires-Dist: attrs>=22.2.0
Requires-Dist: python-dateutil>=2.8.0,<3
Requires-Python: >=3.12
Project-URL: Documentation, https://loops.so/docs
Project-URL: Homepage, https://github.com/doctorgpt-corp/pyloops
Project-URL: Repository, https://github.com/doctorgpt-corp/pyloops
